<?xml version="1.0" ?>

<container xmlns="http://symfony.com/schema/dic/services"
           xmlns:xsi="http://www.w3.org/2001/XMLSchema-instance"
           xsi:schemaLocation="http://symfony.com/schema/dic/services http://symfony.com/schema/dic/services/services-1.0.xsd">

    <parameters>
        <parameter key="ekino.wordpress.twig.extension.comment.class">Ekino\WordpressBundle\Twig\Extension\CommentExtension</parameter>
        <parameter key="ekino.wordpress.twig.extension.option.class">Ekino\WordpressBundle\Twig\Extension\OptionExtension</parameter>
        <parameter key="ekino.wordpress.twig.extension.post.class">Ekino\WordpressBundle\Twig\Extension\PostExtension</parameter>
        <parameter key="ekino.wordpress.twig.extension.post_meta.class">Ekino\WordpressBundle\Twig\Extension\PostMetaExtension</parameter>
        <parameter key="ekino.wordpress.twig.extension.term_taxonomy.class">Ekino\WordpressBundle\Twig\Extension\TermTaxonomyExtension</parameter>
    </parameters>

    <services>
        <service id="ekino.wordpress.twig.extension.comment" class="%ekino.wordpress.twig.extension.comment.class%">
            <tag name="twig.extension" />

            <argument type="service" id="ekino.wordpress.manager.comment" />
        </service>

        <service id="ekino.wordpress.twig.extension.option" class="%ekino.wordpress.twig.extension.option.class%">
            <tag name="twig.extension" />

            <argument type="service" id="ekino.wordpress.manager.option" />
        </service>

        <service id="ekino.wordpress.twig.extension.post" class="%ekino.wordpress.twig.extension.post.class%">
            <tag name="twig.extension" />

            <argument type="service" id="ekino.wordpress.manager.post" />
            <argument type="service" id="ekino.wordpress.twig.extension.option" />
            <argument>%ekino.wordpress.cookie_hash%</argument>
        </service>

        <service id="ekino.wordpress.twig.extension.post_meta" class="%ekino.wordpress.twig.extension.post_meta.class%">
            <tag name="twig.extension" />

            <argument type="service" id="ekino.wordpress.manager.post_meta" />
        </service>

        <service id="ekino.wordpress.twig.extension.term_taxonomy" class="%ekino.wordpress.twig.extension.term_taxonomy.class%">
            <tag name="twig.extension" />

            <argument type="service" id="ekino.wordpress.manager.option" />
        </service>

    </services>
</container>
